{"stepIndex": 16, "stepCount": 42, "step": {"title": "Step 17", "sourceEventIndex": 49, "event": {"type": "analysis", "state": "NOT_FINISHED", "score": 0, "level": 1, "board": [[2, 2, 2, 2, 2, 2, 2, 2, 2, 2, 2, 2, 2, 2, 2, 2, 2, 2, 2, 2, 2, 2, 2, 2, 2, 2, 2, 2, 2, 2, 2, 2, 2, 2, 2, 2, 2, 2, 2, 2, 2, 2, 2, 2, 2, 2, 2, 2, 2, 2, 2, 2, 2, 2, 2, 2, 2, 2, 2, 2, 2, 2, 2, 2], [2, 2, 2, 2, 2, 2, 2, 2, 2, 2, 2, 2, 2, 2, 2, 2, 2, 2, 2, 2, 2, 2, 2, 2, 2, 2, 2, 2, 2, 2, 2, 2, 2, 2, 2, 2, 2, 2, 2, 2, 2, 2, 2, 2, 2, 2, 2, 2, 2, 2, 2, 2, 2, 2, 2, 2, 2, 2, 2, 2, 2, 2, 2, 2], [2, 2, 2, 2, 2, 2, 2, 2, 2, 2, 2, 2, 2, 2, 2, 2, 2, 2, 2, 2, 2, 2, 2, 2, 2, 2, 2, 2, 2, 2, 2, 2, 2, 2, 2, 2, 2, 2, 2, 2, 2, 2, 2, 2, 2, 2, 2, 2, 2, 2, 2, 2, 2, 2, 2, 2, 2, 2, 2, 2, 2, 2, 2, 2], [2, 2, 2, 2, 2, 2, 2, 2, 2, 2, 2, 2, 2, 2, 2, 2, 2, 2, 2, 2, 2, 2, 2, 2, 2, 2, 2, 2, 2, 2, 2, 2, 2, 2, 2, 2, 2, 2, 2, 2, 2, 2, 2, 2, 2, 2, 2, 2, 2, 2, 2, 2, 2, 2, 2, 2, 2, 2, 2, 2, 2, 2, 2, 2], [2, 2, 2, 2, 2, 2, 2, 2, 2, 2, 2, 2, 2, 2, 2, 2, 2, 2, 2, 2, 2, 2, 2, 2, 2, 2, 2, 2, 2, 2, 2, 2, 2, 2, 2, 2, 2, 2, 2, 2, 2, 2, 2, 2, 2, 2, 2, 2, 2, 2, 2, 2, 2, 2, 2, 2, 2, 2, 2, 2, 2, 2, 2, 2], [2, 2, 2, 2, 2, 2, 2, 2, 2, 2, 2, 2, 2, 2, 2, 2, 2, 2, 2, 2, 2, 2, 2, 2, 2, 2, 2, 2, 2, 2, 2, 2, 2, 2, 2, 2, 2, 2, 2, 2, 2, 2, 2, 2, 2, 2, 2, 2, 2, 2, 2, 2, 2, 2, 2, 2, 2, 2, 2, 2, 2, 2, 2, 2], [2, 2, 2, 2, 2, 2, 2, 2, 2, 2, 2, 2, 2, 2, 2, 2, 2, 2, 2, 2, 2, 2, 2, 2, 2, 2, 2, 2, 2, 2, 2, 2, 2, 2, 2, 2, 2, 2, 2, 2, 2, 2, 2, 2, 2, 2, 2, 2, 2, 2, 2, 2, 2, 2, 2, 2, 2, 2, 2, 2, 2, 2, 2, 2], [2, 2, 2, 2, 2, 2, 2, 2, 2, 2, 2, 2, 2, 2, 2, 2, 2, 2, 2, 2, 2, 2, 2, 2, 2, 2, 2, 2, 2, 2, 2, 2, 2, 2, 2, 2, 2, 2, 2, 2, 2, 2, 2, 2, 2, 2, 2, 2, 2, 2, 2, 2, 2, 2, 2, 2, 2, 2, 2, 2, 2, 2, 2, 2], [2, 2, 2, 2, 2, 2, 2, 2, 2, 2, 2, 2, 2, 2, 2, 2, 2, 2, 2, 2, 2, 2, 2, 2, 2, 2, 2, 2, 2, 2, 2, 2, 2, 2, 2, 2, 2, 2, 2, 2, 2, 2, 2, 2, 2, 2, 2, 2, 2, 2, 2, 2, 2, 2, 2, 2, 2, 2, 2, 2, 2, 2, 2, 2], [2, 2, 2, 2, 2, 2, 2, 2, 2, 2, 2, 2, 2, 2, 2, 2, 2, 2, 2, 2, 2, 2, 2, 2, 2, 2, 2, 2, 2, 2, 2, 2, 2, 2, 2, 2, 2, 2, 2, 2, 2, 2, 2, 2, 2, 2, 2, 2, 2, 2, 2, 2, 2, 2, 2, 2, 2, 2, 2, 2, 2, 2, 2, 2], [2, 2, 2, 2, 2, 2, 2, 2, 2, 2, 2, 2, 2, 2, 2, 2, 2, 2, 2, 2, 2, 2, 2, 2, 2, 2, 2, 2, 2, 2, 2, 2, 2, 2, 2, 2, 2, 2, 2, 2, 2, 2, 2, 2, 2, 2, 2, 2, 2, 2, 2, 2, 2, 2, 2, 2, 2, 2, 2, 2, 2, 2, 2, 2], [2, 2, 2, 2, 2, 2, 2, 2, 2, 2, 2, 2, 2, 2, 2, 2, 2, 2, 2, 2, 2, 2, 2, 2, 2, 2, 2, 2, 2, 2, 2, 2, 2, 2, 2, 2, 2, 2, 2, 2, 2, 2, 2, 2, 2, 2, 2, 2, 2, 2, 2, 2, 2, 2, 2, 2, 2, 2, 2, 2, 2, 2, 2, 2], [2, 2, 2, 2, 2, 2, 2, 2, 2, 2, 2, 2, 2, 2, 2, 2, 2, 2, 2, 2, 2, 2, 2, 2, 2, 2, 2, 2, 2, 2, 2, 2, 2, 2, 2, 2, 2, 2, 2, 2, 2, 2, 2, 2, 2, 2, 2, 2, 2, 2, 2, 2, 2, 2, 2, 2, 2, 2, 2, 2, 2, 2, 2, 2], [2, 2, 2, 2, 2, 2, 2, 2, 2, 2, 2, 2, 2, 2, 2, 2, 2, 2, 2, 2, 2, 2, 2, 2, 2, 2, 2, 2, 2, 2, 2, 2, 2, 2, 2, 2, 2, 2, 2, 2, 2, 2, 2, 2, 2, 2, 2, 2, 2, 2, 2, 2, 2, 2, 2, 2, 2, 2, 2, 2, 2, 2, 2, 2], [2, 2, 2, 2, 2, 2, 2, 2, 2, 2, 2, 2, 2, 2, 2, 2, 2, 2, 2, 2, 2, 2, 2, 2, 2, 2, 2, 2, 2, 2, 2, 2, 2, 2, 2, 2, 2, 2, 2, 2, 2, 2, 2, 2, 2, 2, 2, 2, 2, 2, 2, 2, 2, 2, 2, 2, 2, 2, 2, 2, 2, 2, 2, 2], [2, 2, 2, 2, 2, 2, 2, 2, 2, 2, 2, 2, 2, 2, 2, 2, 2, 2, 2, 2, 2, 2, 2, 2, 2, 2, 2, 2, 2, 2, 2, 2, 2, 2, 2, 2, 2, 2, 2, 2, 2, 2, 2, 2, 2, 2, 2, 2, 2, 2, 2, 2, 2, 2, 2, 2, 2, 2, 2, 2, 2, 2, 2, 2], [2, 2, 2, 2, 2, 2, 2, 2, 2, 2, 2, 2, 2, 2, 2, 2, 2, 2, 2, 2, 2, 2, 2, 2, 2, 2, 2, 2, 2, 2, 2, 2, 2, 2, 2, 2, 2, 2, 2, 2, 2, 2, 2, 2, 2, 2, 2, 2, 2, 2, 2, 2, 2, 2, 2, 2, 2, 2, 2, 2, 2, 2, 2, 2], [2, 2, 2, 2, 2, 2, 2, 2, 2, 2, 2, 2, 2, 2, 2, 2, 2, 2, 2, 2, 2, 2, 2, 2, 2, 2, 2, 2, 2, 2, 2, 2, 2, 2, 2, 2, 2, 2, 2, 2, 2, 2, 2, 2, 2, 2, 2, 2, 2, 2, 2, 2, 2, 2, 2, 2, 2, 2, 2, 2, 2, 2, 2, 2], [2, 2, 2, 2, 2, 2, 2, 2, 2, 2, 2, 2, 2, 2, 2, 2, 2, 2, 2, 2, 2, 2, 2, 2, 2, 2, 2, 2, 2, 2, 2, 2, 2, 2, 2, 2, 2, 2, 2, 2, 2, 2, 2, 2, 2, 2, 2, 2, 2, 2, 2, 2, 2, 2, 2, 2, 2, 2, 2, 2, 2, 2, 2, 2], [2, 2, 2, 2, 2, 2, 2, 2, 2, 2, 2, 2, 2, 2, 2, 2, 2, 2, 2, 2, 2, 2, 2, 2, 2, 2, 2, 2, 2, 2, 2, 2, 2, 2, 2, 2, 2, 2, 2, 2, 2, 2, 2, 2, 2, 2, 2, 2, 2, 2, 2, 2, 2, 2, 2, 2, 2, 2, 2, 2, 2, 2, 2, 2], [2, 2, 2, 2, 2, 2, 2, 2, 2, 2, 2, 2, 2, 2, 2, 2, 2, 2, 2, 2, 2, 2, 2, 2, 2, 2, 2, 2, 2, 2, 2, 2, 2, 2, 2, 2, 2, 2, 2, 2, 2, 2, 2, 2, 2, 2, 2, 2, 2, 2, 2, 2, 2, 2, 2, 2, 2, 2, 2, 2, 2, 2, 2, 2], [2, 2, 2, 2, 2, 2, 2, 2, 2, 1, 1, 1, 1, 1, 1, 1, 1, 1, 1, 1, 1, 1, 1, 1, 2, 2, 2, 2, 2, 2, 2, 2, 2, 15, 15, 15, 15, 15, 15, 1, 1, 1, 1, 1, 1, 1, 1, 1, 1, 1, 1, 1, 1, 1, 2, 2, 2, 2, 2, 2, 2, 2, 2, 2], [2, 2, 2, 2, 2, 2, 2, 2, 2, 1, 1, 1, 1, 1, 1, 1, 1, 1, 1, 1, 1, 1, 1, 1, 2, 2, 2, 2, 2, 2, 2, 2, 2, 15, 15, 15, 15, 15, 15, 1, 1, 1, 1, 1, 1, 1, 1, 1, 1, 1, 1, 1, 1, 1, 2, 2, 2, 2, 2, 2, 2, 2, 2, 2], [2, 2, 2, 2, 2, 2, 2, 2, 2, 1, 1, 1, 1, 1, 1, 1, 1, 1, 1, 1, 1, 1, 1, 1, 2, 2, 2, 2, 2, 2, 2, 2, 2, 15, 15, 15, 15, 15, 15, 1, 1, 1, 1, 1, 1, 1, 1, 1, 1, 1, 1, 1, 1, 1, 2, 2, 2, 2, 2, 2, 2, 2, 2, 2], [2, 2, 2, 2, 2, 2, 2, 2, 2, 1, 1, 1, 1, 1, 1, 1, 1, 1, 1, 1, 1, 1, 1, 1, 2, 2, 2, 2, 2, 2, 2, 2, 2, 15, 15, 15, 15, 15, 15, 1, 1, 1, 1, 1, 1, 1, 1, 1, 1, 1, 1, 1, 1, 1, 2, 2, 2, 2, 2, 2, 2, 2, 2, 2], [2, 2, 2, 2, 2, 2, 2, 2, 2, 1, 1, 1, 1, 1, 1, 1, 1, 1, 1, 1, 1, 1, 1, 1, 2, 2, 2, 2, 2, 2, 2, 2, 2, 15, 15, 15, 15, 15, 15, 1, 1, 1, 1, 1, 1, 1, 1, 1, 1, 1, 1, 1, 1, 1, 2, 2, 2, 2, 2, 2, 2, 2, 2, 2], [2, 2, 2, 2, 2, 2, 2, 2, 2, 1, 1, 1, 1, 1, 1, 1, 1, 1, 1, 1, 1, 1, 1, 1, 2, 2, 2, 2, 2, 2, 2, 2, 2, 15, 15, 15, 15, 15, 15, 1, 1, 1, 1, 1, 4, 4, 4, 4, 4, 1, 1, 1, 1, 1, 2, 2, 2, 2, 2, 2, 2, 2, 2, 2], [2, 2, 2, 2, 2, 2, 2, 2, 2, 1, 1, 1, 1, 1, 1, 1, 1, 1, 1, 1, 1, 1, 1, 1, 2, 2, 2, 2, 2, 2, 2, 2, 2, 15, 15, 15, 15, 15, 15, 1, 1, 1, 1, 1, 4, 1, 1, 1, 4, 1, 1, 1, 1, 1, 2, 2, 2, 2, 2, 2, 2, 2, 2, 2], [2, 2, 2, 2, 2, 2, 2, 2, 2, 1, 1, 1, 1, 1, 1, 1, 1, 1, 1, 1, 1, 1, 1, 1, 2, 2, 2, 2, 2, 2, 2, 2, 2, 15, 15, 15, 15, 15, 15, 1, 1, 1, 1, 1, 4, 1, 1, 1, 4, 1, 1, 1, 1, 1, 2, 2, 2, 2, 2, 2, 2, 2, 2, 2], [2, 2, 2, 2, 2, 2, 2, 2, 2, 1, 1, 1, 1, 1, 1, 1, 1, 1, 1, 1, 1, 1, 1, 1, 2, 2, 2, 2, 2, 2, 2, 2, 2, 15, 15, 15, 15, 15, 15, 1, 1, 1, 1, 1, 4, 1, 1, 1, 4, 1, 1, 1, 1, 1, 2, 2, 2, 2, 2, 2, 2, 2, 2, 2], [2, 2, 2, 2, 2, 2, 2, 2, 2, 1, 1, 1, 1, 1, 1, 1, 1, 1, 1, 1, 1, 1, 1, 1, 1, 1, 1, 1, 1, 1, 14, 14, 14, 15, 15, 15, 15, 15, 15, 1, 1, 1, 1, 1, 4, 4, 4, 4, 4, 1, 1, 1, 1, 1, 2, 2, 2, 2, 2, 2, 2, 2, 2, 2], [2, 2, 2, 2, 2, 2, 2, 2, 2, 1, 1, 1, 1, 1, 1, 1, 1, 1, 1, 1, 1, 1, 1, 1, 1, 1, 1, 1, 1, 1, 14, 0, 14, 15, 15, 15, 15, 15, 15, 1, 1, 1, 1, 1, 1, 1, 1, 1, 1, 1, 1, 1, 1, 1, 2, 2, 2, 2, 2, 2, 2, 2, 2, 2], [2, 2, 2, 2, 2, 2, 2, 2, 2, 1, 1, 4, 4, 4, 4, 4, 1, 1, 1, 1, 1, 1, 1, 1, 1, 1, 1, 1, 1, 1, 14, 14, 14, 15, 15, 15, 15, 15, 15, 1, 1, 1, 1, 1, 1, 1, 1, 1, 1, 1, 1, 1, 1, 1, 2, 2, 2, 2, 2, 2, 2, 2, 2, 2], [2, 2, 2, 2, 2, 2, 2, 2, 2, 1, 1, 4, 14, 14, 14, 4, 1, 1, 1, 1, 1, 1, 1, 1, 2, 2, 2, 2, 2, 2, 2, 2, 2, 15, 15, 15, 15, 15, 15, 1, 1, 1, 1, 1, 1, 1, 1, 1, 1, 1, 1, 1, 1, 1, 2, 2, 2, 2, 2, 2, 2, 2, 2, 2], [2, 2, 2, 2, 2, 2, 2, 2, 2, 1, 1, 4, 14, 4, 14, 4, 1, 1, 1, 1, 1, 1, 1, 1, 2, 2, 2, 2, 2, 2, 2, 2, 2, 15, 15, 15, 15, 15, 15, 1, 1, 1, 1, 1, 1, 1, 1, 1, 1, 1, 1, 1, 1, 1, 2, 2, 2, 2, 2, 2, 2, 2, 2, 2], [2, 2, 2, 2, 2, 2, 2, 2, 2, 1, 1, 4, 14, 14, 14, 4, 1, 1, 1, 1, 1, 1, 1, 1, 2, 2, 2, 2, 2, 2, 2, 2, 2, 15, 15, 15, 15, 15, 15, 1, 1, 1, 1, 1, 1, 1, 1, 1, 1, 1, 1, 1, 1, 1, 2, 2, 2, 2, 2, 2, 2, 2, 2, 2], [2, 2, 2, 2, 2, 2, 2, 2, 2, 1, 1, 4, 4, 4, 4, 4, 1, 1, 1, 1, 1, 1, 1, 1, 2, 2, 2, 2, 2, 2, 2, 2, 2, 15, 15, 15, 15, 15, 15, 1, 1, 1, 1, 1, 1, 1, 1, 1, 1, 1, 1, 1, 1, 1, 2, 2, 2, 2, 2, 2, 2, 2, 2, 2], [2, 2, 2, 2, 2, 2, 2, 2, 2, 1, 1, 1, 1, 1, 1, 1, 1, 1, 1, 1, 1, 1, 1, 1, 2, 2, 2, 2, 2, 2, 2, 2, 2, 15, 15, 15, 15, 15, 15, 1, 1, 1, 1, 1, 1, 1, 1, 1, 1, 1, 1, 1, 1, 1, 2, 2, 2, 2, 2, 2, 2, 2, 2, 2], [2, 2, 2, 2, 2, 2, 2, 2, 2, 1, 1, 1, 1, 1, 1, 1, 1, 1, 1, 1, 1, 1, 1, 1, 2, 2, 2, 2, 2, 2, 2, 2, 2, 15, 15, 15, 15, 15, 15, 1, 1, 1, 1, 1, 1, 1, 1, 1, 1, 1, 1, 1, 1, 1, 2, 2, 2, 2, 2, 2, 2, 2, 2, 2], [2, 2, 2, 2, 2, 2, 2, 2, 2, 1, 1, 1, 1, 1, 1, 1, 1, 1, 1, 1, 1, 1, 1, 1, 2, 2, 2, 2, 2, 2, 2, 2, 2, 15, 15, 15, 15, 15, 15, 1, 1, 1, 1, 1, 1, 1, 1, 1, 1, 1, 1, 1, 1, 1, 2, 2, 2, 2, 2, 2, 2, 2, 2, 2], [2, 2, 2, 2, 2, 2, 2, 2, 2, 1, 1, 1, 1, 1, 1, 1, 1, 1, 1, 1, 1, 1, 1, 1, 2, 2, 2, 2, 2, 2, 2, 2, 2, 15, 15, 15, 15, 15, 15, 1, 1, 1, 1, 1, 1, 1, 1, 1, 1, 1, 1, 1, 1, 1, 2, 2, 2, 2, 2, 2, 2, 2, 2, 2], [2, 2, 2, 2, 2, 2, 2, 2, 2, 1, 1, 1, 1, 1, 1, 1, 1, 1, 1, 1, 1, 1, 1, 1, 2, 2, 2, 2, 2, 2, 2, 2, 2, 15, 15, 15, 15, 15, 15, 1, 1, 1, 1, 1, 1, 1, 1, 1, 1, 1, 1, 1, 1, 1, 2, 2, 2, 2, 2, 2, 2, 2, 2, 2], [2, 2, 2, 2, 2, 2, 2, 2, 2, 2, 2, 2, 2, 2, 2, 2, 2, 2, 2, 2, 2, 2, 2, 2, 2, 2, 2, 2, 2, 2, 2, 2, 2, 2, 2, 2, 2, 2, 2, 2, 2, 2, 2, 2, 2, 2, 2, 2, 2, 2, 2, 2, 2, 2, 2, 2, 2, 2, 2, 2, 2, 2, 2, 2], [2, 2, 2, 2, 2, 2, 2, 2, 2, 2, 2, 2, 2, 2, 2, 2, 2, 2, 2, 2, 2, 2, 2, 2, 2, 2, 2, 2, 2, 2, 2, 2, 2, 2, 2, 2, 2, 2, 2, 2, 2, 2, 2, 2, 2, 2, 2, 2, 2, 2, 2, 2, 2, 2, 2, 2, 2, 2, 2, 2, 2, 2, 2, 2], [2, 2, 2, 2, 2, 2, 2, 2, 2, 2, 2, 2, 2, 2, 2, 2, 2, 2, 2, 2, 2, 2, 2, 2, 2, 2, 2, 2, 2, 2, 2, 2, 2, 2, 2, 2, 2, 2, 2, 2, 2, 2, 2, 2, 2, 2, 2, 2, 2, 2, 2, 2, 2, 2, 2, 2, 2, 2, 2, 2, 2, 2, 2, 2], [2, 2, 2, 2, 2, 2, 2, 2, 2, 2, 2, 2, 2, 2, 2, 2, 2, 2, 2, 2, 2, 2, 2, 2, 2, 2, 2, 2, 2, 2, 2, 2, 2, 2, 2, 2, 2, 2, 2, 2, 2, 2, 2, 2, 2, 2, 2, 2, 2, 2, 2, 2, 2, 2, 2, 2, 2, 2, 2, 2, 2, 2, 2, 2], [2, 2, 2, 2, 2, 2, 2, 2, 2, 2, 2, 2, 2, 2, 2, 2, 2, 2, 2, 2, 2, 2, 2, 2, 2, 2, 2, 2, 2, 2, 2, 2, 2, 2, 2, 2, 2, 2, 2, 2, 2, 2, 2, 2, 2, 2, 2, 2, 2, 2, 2, 2, 2, 2, 2, 2, 2, 2, 2, 2, 2, 2, 2, 2], [2, 2, 2, 2, 2, 2, 2, 2, 2, 2, 2, 2, 2, 2, 2, 2, 2, 2, 2, 2, 2, 2, 2, 2, 2, 2, 2, 2, 2, 2, 2, 2, 2, 2, 2, 2, 2, 2, 2, 2, 2, 2, 2, 2, 2, 2, 2, 2, 2, 2, 2, 2, 2, 2, 2, 2, 2, 2, 2, 2, 2, 2, 2, 2], [2, 2, 2, 2, 2, 2, 2, 2, 2, 2, 2, 2, 2, 2, 2, 2, 2, 2, 2, 2, 2, 2, 2, 2, 2, 2, 2, 2, 2, 2, 2, 2, 2, 2, 2, 2, 2, 2, 2, 2, 2, 2, 2, 2, 2, 2, 2, 2, 2, 2, 2, 2, 2, 2, 2, 2, 2, 2, 2, 2, 2, 2, 2, 2], [2, 2, 2, 2, 2, 2, 2, 2, 2, 2, 2, 2, 2, 2, 2, 2, 2, 2, 2, 2, 2, 2, 2, 2, 2, 2, 2, 2, 2, 2, 2, 2, 2, 2, 2, 2, 2, 2, 2, 2, 2, 2, 2, 2, 2, 2, 2, 2, 2, 2, 2, 2, 2, 2, 2, 2, 2, 2, 2, 2, 2, 2, 2, 2], [2, 2, 2, 2, 2, 2, 2, 2, 2, 2, 2, 2, 2, 2, 2, 2, 2, 2, 2, 2, 2, 2, 2, 2, 2, 2, 2, 2, 2, 2, 2, 2, 2, 2, 2, 2, 2, 2, 2, 2, 2, 2, 2, 2, 2, 2, 2, 2, 2, 2, 2, 2, 2, 2, 2, 2, 2, 2, 2, 2, 2, 2, 2, 2], [2, 2, 2, 2, 2, 2, 2, 2, 2, 2, 2, 2, 2, 2, 2, 2, 2, 2, 2, 2, 2, 2, 2, 2, 2, 2, 2, 2, 2, 2, 2, 2, 2, 2, 2, 2, 2, 2, 2, 2, 2, 2, 2, 2, 2, 2, 2, 2, 2, 2, 2, 2, 2, 2, 2, 2, 2, 2, 2, 2, 2, 2, 2, 2], [2, 2, 2, 2, 2, 2, 2, 2, 2, 2, 2, 2, 2, 2, 2, 2, 2, 2, 2, 2, 2, 2, 2, 2, 2, 2, 2, 2, 2, 2, 2, 2, 2, 2, 2, 2, 2, 2, 2, 2, 2, 2, 2, 2, 2, 2, 2, 2, 2, 2, 2, 2, 2, 2, 2, 2, 2, 2, 2, 2, 2, 2, 2, 2], [2, 2, 2, 2, 2, 2, 2, 2, 2, 2, 2, 2, 2, 2, 2, 2, 2, 2, 2, 2, 2, 2, 2, 2, 2, 2, 2, 2, 2, 2, 2, 2, 2, 2, 2, 2, 2, 2, 2, 2, 2, 2, 2, 2, 2, 2, 2, 2, 2, 2, 2, 2, 2, 2, 2, 2, 2, 2, 2, 2, 2, 2, 2, 2], [2, 2, 2, 2, 2, 2, 2, 2, 2, 2, 2, 2, 2, 2, 2, 2, 2, 2, 2, 2, 2, 2, 2, 2, 2, 2, 2, 2, 2, 2, 2, 2, 2, 2, 2, 2, 2, 2, 2, 2, 2, 2, 2, 2, 2, 2, 2, 2, 2, 2, 2, 2, 2, 2, 2, 2, 2, 2, 2, 2, 2, 2, 2, 2], [2, 2, 2, 2, 2, 2, 2, 2, 2, 2, 2, 2, 2, 2, 2, 2, 2, 2, 2, 2, 2, 2, 2, 2, 2, 2, 2, 2, 2, 2, 2, 2, 2, 2, 2, 2, 2, 2, 2, 2, 2, 2, 2, 2, 2, 2, 2, 2, 2, 2, 2, 2, 2, 2, 2, 2, 2, 2, 2, 2, 2, 2, 2, 2], [2, 2, 2, 2, 2, 2, 2, 2, 2, 2, 2, 2, 2, 2, 2, 2, 2, 2, 2, 2, 2, 2, 2, 2, 2, 2, 2, 2, 2, 2, 2, 2, 2, 2, 2, 2, 2, 2, 2, 2, 2, 2, 2, 2, 2, 2, 2, 2, 2, 2, 2, 2, 2, 2, 2, 2, 2, 2, 2, 2, 2, 2, 2, 2], [2, 2, 2, 2, 2, 2, 2, 2, 2, 2, 2, 2, 2, 2, 2, 2, 2, 2, 2, 2, 2, 2, 2, 2, 2, 2, 2, 2, 2, 2, 2, 2, 2, 2, 2, 2, 2, 2, 2, 2, 2, 2, 2, 2, 2, 2, 2, 2, 2, 2, 2, 2, 2, 2, 2, 2, 2, 2, 2, 2, 2, 2, 2, 2], [2, 2, 2, 2, 2, 2, 2, 2, 2, 2, 2, 2, 2, 2, 2, 2, 2, 2, 2, 2, 2, 2, 2, 2, 2, 2, 2, 2, 2, 2, 2, 2, 2, 2, 2, 2, 2, 2, 2, 2, 2, 2, 2, 2, 2, 2, 2, 2, 2, 2, 2, 2, 2, 2, 2, 2, 2, 2, 2, 2, 2, 2, 2, 2], [2, 2, 2, 2, 2, 2, 2, 2, 2, 2, 2, 2, 2, 2, 2, 2, 2, 2, 2, 2, 2, 2, 2, 2, 2, 2, 2, 2, 2, 2, 2, 2, 2, 2, 2, 2, 2, 2, 2, 2, 2, 2, 2, 2, 2, 2, 2, 2, 2, 2, 2, 2, 2, 2, 2, 2, 2, 2, 2, 2, 2, 2, 2, 2], [2, 2, 2, 2, 2, 2, 2, 2, 2, 2, 2, 2, 2, 2, 2, 2, 2, 2, 2, 2, 2, 2, 2, 2, 2, 2, 2, 2, 2, 2, 2, 2, 2, 2, 2, 2, 2, 2, 2, 2, 2, 2, 2, 2, 2, 2, 2, 2, 2, 2, 2, 2, 2, 2, 2, 2, 2, 2, 2, 2, 2, 2, 2, 2], [2, 2, 2, 2, 2, 2, 2, 2, 2, 2, 2, 2, 2, 2, 2, 2, 2, 2, 2, 2, 2, 2, 2, 2, 2, 2, 2, 2, 2, 2, 2, 2, 2, 2, 2, 2, 2, 2, 2, 2, 2, 2, 2, 2, 2, 2, 2, 2, 2, 2, 2, 2, 2, 2, 2, 2, 2, 2, 2, 2, 2, 2, 2, 2], [2, 2, 2, 2, 2, 2, 2, 2, 2, 2, 2, 2, 2, 2, 2, 2, 2, 2, 2, 2, 2, 2, 2, 2, 2, 2, 2, 2, 2, 2, 2, 2, 2, 2, 2, 2, 2, 2, 2, 2, 2, 2, 2, 2, 2, 2, 2, 2, 2, 2, 2, 2, 2, 2, 2, 2, 2, 2, 2, 2, 2, 2, 2, 2], [4, 4, 4, 4, 4, 4, 4, 4, 4, 4, 4, 4, 4, 4, 4, 4, 4, 4, 4, 4, 4, 4, 4, 4, 4, 4, 4, 4, 4, 4, 4, 4, 4, 4, 4, 4, 4, 4, 4, 4, 4, 4, 4, 4, 4, 4, 4, 0, 0, 0, 0, 0, 0, 0, 0, 0, 0, 0, 0, 0, 0, 0, 0, 0]]}, "boardEvent": {"type": "action", "action_display": "RIGHT", "action_name": "ACTION4", "state": "NOT_FINISHED", "reward": 0.0, "score": 0, "level": 1, "board": [[2, 2, 2, 2, 2, 2, 2, 2, 2, 2, 2, 2, 2, 2, 2, 2, 2, 2, 2, 2, 2, 2, 2, 2, 2, 2, 2, 2, 2, 2, 2, 2, 2, 2, 2, 2, 2, 2, 2, 2, 2, 2, 2, 2, 2, 2, 2, 2, 2, 2, 2, 2, 2, 2, 2, 2, 2, 2, 2, 2, 2, 2, 2, 2], [2, 2, 2, 2, 2, 2, 2, 2, 2, 2, 2, 2, 2, 2, 2, 2, 2, 2, 2, 2, 2, 2, 2, 2, 2, 2, 2, 2, 2, 2, 2, 2, 2, 2, 2, 2, 2, 2, 2, 2, 2, 2, 2, 2, 2, 2, 2, 2, 2, 2, 2, 2, 2, 2, 2, 2, 2, 2, 2, 2, 2, 2, 2, 2], [2, 2, 2, 2, 2, 2, 2, 2, 2, 2, 2, 2, 2, 2, 2, 2, 2, 2, 2, 2, 2, 2, 2, 2, 2, 2, 2, 2, 2, 2, 2, 2, 2, 2, 2, 2, 2, 2, 2, 2, 2, 2, 2, 2, 2, 2, 2, 2, 2, 2, 2, 2, 2, 2, 2, 2, 2, 2, 2, 2, 2, 2, 2, 2], [2, 2, 2, 2, 2, 2, 2, 2, 2, 2, 2, 2, 2, 2, 2, 2, 2, 2, 2, 2, 2, 2, 2, 2, 2, 2, 2, 2, 2, 2, 2, 2, 2, 2, 2, 2, 2, 2, 2, 2, 2, 2, 2, 2, 2, 2, 2, 2, 2, 2, 2, 2, 2, 2, 2, 2, 2, 2, 2, 2, 2, 2, 2, 2], [2, 2, 2, 2, 2, 2, 2, 2, 2, 2, 2, 2, 2, 2, 2, 2, 2, 2, 2, 2, 2, 2, 2, 2, 2, 2, 2, 2, 2, 2, 2, 2, 2, 2, 2, 2, 2, 2, 2, 2, 2, 2, 2, 2, 2, 2, 2, 2, 2, 2, 2, 2, 2, 2, 2, 2, 2, 2, 2, 2, 2, 2, 2, 2], [2, 2, 2, 2, 2, 2, 2, 2, 2, 2, 2, 2, 2, 2, 2, 2, 2, 2, 2, 2, 2, 2, 2, 2, 2, 2, 2, 2, 2, 2, 2, 2, 2, 2, 2, 2, 2, 2, 2, 2, 2, 2, 2, 2, 2, 2, 2, 2, 2, 2, 2, 2, 2, 2, 2, 2, 2, 2, 2, 2, 2, 2, 2, 2], [2, 2, 2, 2, 2, 2, 2, 2, 2, 2, 2, 2, 2, 2, 2, 2, 2, 2, 2, 2, 2, 2, 2, 2, 2, 2, 2, 2, 2, 2, 2, 2, 2, 2, 2, 2, 2, 2, 2, 2, 2, 2, 2, 2, 2, 2, 2, 2, 2, 2, 2, 2, 2, 2, 2, 2, 2, 2, 2, 2, 2, 2, 2, 2], [2, 2, 2, 2, 2, 2, 2, 2, 2, 2, 2, 2, 2, 2, 2, 2, 2, 2, 2, 2, 2, 2, 2, 2, 2, 2, 2, 2, 2, 2, 2, 2, 2, 2, 2, 2, 2, 2, 2, 2, 2, 2, 2, 2, 2, 2, 2, 2, 2, 2, 2, 2, 2, 2, 2, 2, 2, 2, 2, 2, 2, 2, 2, 2], [2, 2, 2, 2, 2, 2, 2, 2, 2, 2, 2, 2, 2, 2, 2, 2, 2, 2, 2, 2, 2, 2, 2, 2, 2, 2, 2, 2, 2, 2, 2, 2, 2, 2, 2, 2, 2, 2, 2, 2, 2, 2, 2, 2, 2, 2, 2, 2, 2, 2, 2, 2, 2, 2, 2, 2, 2, 2, 2, 2, 2, 2, 2, 2], [2, 2, 2, 2, 2, 2, 2, 2, 2, 2, 2, 2, 2, 2, 2, 2, 2, 2, 2, 2, 2, 2, 2, 2, 2, 2, 2, 2, 2, 2, 2, 2, 2, 2, 2, 2, 2, 2, 2, 2, 2, 2, 2, 2, 2, 2, 2, 2, 2, 2, 2, 2, 2, 2, 2, 2, 2, 2, 2, 2, 2, 2, 2, 2], [2, 2, 2, 2, 2, 2, 2, 2, 2, 2, 2, 2, 2, 2, 2, 2, 2, 2, 2, 2, 2, 2, 2, 2, 2, 2, 2, 2, 2, 2, 2, 2, 2, 2, 2, 2, 2, 2, 2, 2, 2, 2, 2, 2, 2, 2, 2, 2, 2, 2, 2, 2, 2, 2, 2, 2, 2, 2, 2, 2, 2, 2, 2, 2], [2, 2, 2, 2, 2, 2, 2, 2, 2, 2, 2, 2, 2, 2, 2, 2, 2, 2, 2, 2, 2, 2, 2, 2, 2, 2, 2, 2, 2, 2, 2, 2, 2, 2, 2, 2, 2, 2, 2, 2, 2, 2, 2, 2, 2, 2, 2, 2, 2, 2, 2, 2, 2, 2, 2, 2, 2, 2, 2, 2, 2, 2, 2, 2], [2, 2, 2, 2, 2, 2, 2, 2, 2, 2, 2, 2, 2, 2, 2, 2, 2, 2, 2, 2, 2, 2, 2, 2, 2, 2, 2, 2, 2, 2, 2, 2, 2, 2, 2, 2, 2, 2, 2, 2, 2, 2, 2, 2, 2, 2, 2, 2, 2, 2, 2, 2, 2, 2, 2, 2, 2, 2, 2, 2, 2, 2, 2, 2], [2, 2, 2, 2, 2, 2, 2, 2, 2, 2, 2, 2, 2, 2, 2, 2, 2, 2, 2, 2, 2, 2, 2, 2, 2, 2, 2, 2, 2, 2, 2, 2, 2, 2, 2, 2, 2, 2, 2, 2, 2, 2, 2, 2, 2, 2, 2, 2, 2, 2, 2, 2, 2, 2, 2, 2, 2, 2, 2, 2, 2, 2, 2, 2], [2, 2, 2, 2, 2, 2, 2, 2, 2, 2, 2, 2, 2, 2, 2, 2, 2, 2, 2, 2, 2, 2, 2, 2, 2, 2, 2, 2, 2, 2, 2, 2, 2, 2, 2, 2, 2, 2, 2, 2, 2, 2, 2, 2, 2, 2, 2, 2, 2, 2, 2, 2, 2, 2, 2, 2, 2, 2, 2, 2, 2, 2, 2, 2], [2, 2, 2, 2, 2, 2, 2, 2, 2, 2, 2, 2, 2, 2, 2, 2, 2, 2, 2, 2, 2, 2, 2, 2, 2, 2, 2, 2, 2, 2, 2, 2, 2, 2, 2, 2, 2, 2, 2, 2, 2, 2, 2, 2, 2, 2, 2, 2, 2, 2, 2, 2, 2, 2, 2, 2, 2, 2, 2, 2, 2, 2, 2, 2], [2, 2, 2, 2, 2, 2, 2, 2, 2, 2, 2, 2, 2, 2, 2, 2, 2, 2, 2, 2, 2, 2, 2, 2, 2, 2, 2, 2, 2, 2, 2, 2, 2, 2, 2, 2, 2, 2, 2, 2, 2, 2, 2, 2, 2, 2, 2, 2, 2, 2, 2, 2, 2, 2, 2, 2, 2, 2, 2, 2, 2, 2, 2, 2], [2, 2, 2, 2, 2, 2, 2, 2, 2, 2, 2, 2, 2, 2, 2, 2, 2, 2, 2, 2, 2, 2, 2, 2, 2, 2, 2, 2, 2, 2, 2, 2, 2, 2, 2, 2, 2, 2, 2, 2, 2, 2, 2, 2, 2, 2, 2, 2, 2, 2, 2, 2, 2, 2, 2, 2, 2, 2, 2, 2, 2, 2, 2, 2], [2, 2, 2, 2, 2, 2, 2, 2, 2, 2, 2, 2, 2, 2, 2, 2, 2, 2, 2, 2, 2, 2, 2, 2, 2, 2, 2, 2, 2, 2, 2, 2, 2, 2, 2, 2, 2, 2, 2, 2, 2, 2, 2, 2, 2, 2, 2, 2, 2, 2, 2, 2, 2, 2, 2, 2, 2, 2, 2, 2, 2, 2, 2, 2], [2, 2, 2, 2, 2, 2, 2, 2, 2, 2, 2, 2, 2, 2, 2, 2, 2, 2, 2, 2, 2, 2, 2, 2, 2, 2, 2, 2, 2, 2, 2, 2, 2, 2, 2, 2, 2, 2, 2, 2, 2, 2, 2, 2, 2, 2, 2, 2, 2, 2, 2, 2, 2, 2, 2, 2, 2, 2, 2, 2, 2, 2, 2, 2], [2, 2, 2, 2, 2, 2, 2, 2, 2, 2, 2, 2, 2, 2, 2, 2, 2, 2, 2, 2, 2, 2, 2, 2, 2, 2, 2, 2, 2, 2, 2, 2, 2, 2, 2, 2, 2, 2, 2, 2, 2, 2, 2, 2, 2, 2, 2, 2, 2, 2, 2, 2, 2, 2, 2, 2, 2, 2, 2, 2, 2, 2, 2, 2], [2, 2, 2, 2, 2, 2, 2, 2, 2, 1, 1, 1, 1, 1, 1, 1, 1, 1, 1, 1, 1, 1, 1, 1, 2, 2, 2, 2, 2, 2, 2, 2, 2, 15, 15, 15, 15, 15, 15, 1, 1, 1, 1, 1, 1, 1, 1, 1, 1, 1, 1, 1, 1, 1, 2, 2, 2, 2, 2, 2, 2, 2, 2, 2], [2, 2, 2, 2, 2, 2, 2, 2, 2, 1, 1, 1, 1, 1, 1, 1, 1, 1, 1, 1, 1, 1, 1, 1, 2, 2, 2, 2, 2, 2, 2, 2, 2, 15, 15, 15, 15, 15, 15, 1, 1, 1, 1, 1, 1, 1, 1, 1, 1, 1, 1, 1, 1, 1, 2, 2, 2, 2, 2, 2, 2, 2, 2, 2], [2, 2, 2, 2, 2, 2, 2, 2, 2, 1, 1, 1, 1, 1, 1, 1, 1, 1, 1, 1, 1, 1, 1, 1, 2, 2, 2, 2, 2, 2, 2, 2, 2, 15, 15, 15, 15, 15, 15, 1, 1, 1, 1, 1, 1, 1, 1, 1, 1, 1, 1, 1, 1, 1, 2, 2, 2, 2, 2, 2, 2, 2, 2, 2], [2, 2, 2, 2, 2, 2, 2, 2, 2, 1, 1, 1, 1, 1, 1, 1, 1, 1, 1, 1, 1, 1, 1, 1, 2, 2, 2, 2, 2, 2, 2, 2, 2, 15, 15, 15, 15, 15, 15, 1, 1, 1, 1, 1, 1, 1, 1, 1, 1, 1, 1, 1, 1, 1, 2, 2, 2, 2, 2, 2, 2, 2, 2, 2], [2, 2, 2, 2, 2, 2, 2, 2, 2, 1, 1, 1, 1, 1, 1, 1, 1, 1, 1, 1, 1, 1, 1, 1, 2, 2, 2, 2, 2, 2, 2, 2, 2, 15, 15, 15, 15, 15, 15, 1, 1, 1, 1, 1, 1, 1, 1, 1, 1, 1, 1, 1, 1, 1, 2, 2, 2, 2, 2, 2, 2, 2, 2, 2], [2, 2, 2, 2, 2, 2, 2, 2, 2, 1, 1, 1, 1, 1, 1, 1, 1, 1, 1, 1, 1, 1, 1, 1, 2, 2, 2, 2, 2, 2, 2, 2, 2, 15, 15, 15, 15, 15, 15, 1, 1, 1, 1, 1, 4, 4, 4, 4, 4, 1, 1, 1, 1, 1, 2, 2, 2, 2, 2, 2, 2, 2, 2, 2], [2, 2, 2, 2, 2, 2, 2, 2, 2, 1, 1, 1, 1, 1, 1, 1, 1, 1, 1, 1, 1, 1, 1, 1, 2, 2, 2, 2, 2, 2, 2, 2, 2, 15, 15, 15, 15, 15, 15, 1, 1, 1, 1, 1, 4, 1, 1, 1, 4, 1, 1, 1, 1, 1, 2, 2, 2, 2, 2, 2, 2, 2, 2, 2], [2, 2, 2, 2, 2, 2, 2, 2, 2, 1, 1, 1, 1, 1, 1, 1, 1, 1, 1, 1, 1, 1, 1, 1, 2, 2, 2, 2, 2, 2, 2, 2, 2, 15, 15, 15, 15, 15, 15, 1, 1, 1, 1, 1, 4, 1, 1, 1, 4, 1, 1, 1, 1, 1, 2, 2, 2, 2, 2, 2, 2, 2, 2, 2], [2, 2, 2, 2, 2, 2, 2, 2, 2, 1, 1, 1, 1, 1, 1, 1, 1, 1, 1, 1, 1, 1, 1, 1, 2, 2, 2, 2, 2, 2, 2, 2, 2, 15, 15, 15, 15, 15, 15, 1, 1, 1, 1, 1, 4, 1, 1, 1, 4, 1, 1, 1, 1, 1, 2, 2, 2, 2, 2, 2, 2, 2, 2, 2], [2, 2, 2, 2, 2, 2, 2, 2, 2, 1, 1, 1, 1, 1, 1, 1, 1, 1, 1, 1, 1, 1, 1, 1, 1, 1, 1, 1, 1, 1, 14, 14, 14, 15, 15, 15, 15, 15, 15, 1, 1, 1, 1, 1, 4, 4, 4, 4, 4, 1, 1, 1, 1, 1, 2, 2, 2, 2, 2, 2, 2, 2, 2, 2], [2, 2, 2, 2, 2, 2, 2, 2, 2, 1, 1, 1, 1, 1, 1, 1, 1, 1, 1, 1, 1, 1, 1, 1, 1, 1, 1, 1, 1, 1, 14, 0, 14, 15, 15, 15, 15, 15, 15, 1, 1, 1, 1, 1, 1, 1, 1, 1, 1, 1, 1, 1, 1, 1, 2, 2, 2, 2, 2, 2, 2, 2, 2, 2], [2, 2, 2, 2, 2, 2, 2, 2, 2, 1, 1, 4, 4, 4, 4, 4, 1, 1, 1, 1, 1, 1, 1, 1, 1, 1, 1, 1, 1, 1, 14, 14, 14, 15, 15, 15, 15, 15, 15, 1, 1, 1, 1, 1, 1, 1, 1, 1, 1, 1, 1, 1, 1, 1, 2, 2, 2, 2, 2, 2, 2, 2, 2, 2], [2, 2, 2, 2, 2, 2, 2, 2, 2, 1, 1, 4, 14, 14, 14, 4, 1, 1, 1, 1, 1, 1, 1, 1, 2, 2, 2, 2, 2, 2, 2, 2, 2, 15, 15, 15, 15, 15, 15, 1, 1, 1, 1, 1, 1, 1, 1, 1, 1, 1, 1, 1, 1, 1, 2, 2, 2, 2, 2, 2, 2, 2, 2, 2], [2, 2, 2, 2, 2, 2, 2, 2, 2, 1, 1, 4, 14, 4, 14, 4, 1, 1, 1, 1, 1, 1, 1, 1, 2, 2, 2, 2, 2, 2, 2, 2, 2, 15, 15, 15, 15, 15, 15, 1, 1, 1, 1, 1, 1, 1, 1, 1, 1, 1, 1, 1, 1, 1, 2, 2, 2, 2, 2, 2, 2, 2, 2, 2], [2, 2, 2, 2, 2, 2, 2, 2, 2, 1, 1, 4, 14, 14, 14, 4, 1, 1, 1, 1, 1, 1, 1, 1, 2, 2, 2, 2, 2, 2, 2, 2, 2, 15, 15, 15, 15, 15, 15, 1, 1, 1, 1, 1, 1, 1, 1, 1, 1, 1, 1, 1, 1, 1, 2, 2, 2, 2, 2, 2, 2, 2, 2, 2], [2, 2, 2, 2, 2, 2, 2, 2, 2, 1, 1, 4, 4, 4, 4, 4, 1, 1, 1, 1, 1, 1, 1, 1, 2, 2, 2, 2, 2, 2, 2, 2, 2, 15, 15, 15, 15, 15, 15, 1, 1, 1, 1, 1, 1, 1, 1, 1, 1, 1, 1, 1, 1, 1, 2, 2, 2, 2, 2, 2, 2, 2, 2, 2], [2, 2, 2, 2, 2, 2, 2, 2, 2, 1, 1, 1, 1, 1, 1, 1, 1, 1, 1, 1, 1, 1, 1, 1, 2, 2, 2, 2, 2, 2, 2, 2, 2, 15, 15, 15, 15, 15, 15, 1, 1, 1, 1, 1, 1, 1, 1, 1, 1, 1, 1, 1, 1, 1, 2, 2, 2, 2, 2, 2, 2, 2, 2, 2], [2, 2, 2, 2, 2, 2, 2, 2, 2, 1, 1, 1, 1, 1, 1, 1, 1, 1, 1, 1, 1, 1, 1, 1, 2, 2, 2, 2, 2, 2, 2, 2, 2, 15, 15, 15, 15, 15, 15, 1, 1, 1, 1, 1, 1, 1, 1, 1, 1, 1, 1, 1, 1, 1, 2, 2, 2, 2, 2, 2, 2, 2, 2, 2], [2, 2, 2, 2, 2, 2, 2, 2, 2, 1, 1, 1, 1, 1, 1, 1, 1, 1, 1, 1, 1, 1, 1, 1, 2, 2, 2, 2, 2, 2, 2, 2, 2, 15, 15, 15, 15, 15, 15, 1, 1, 1, 1, 1, 1, 1, 1, 1, 1, 1, 1, 1, 1, 1, 2, 2, 2, 2, 2, 2, 2, 2, 2, 2], [2, 2, 2, 2, 2, 2, 2, 2, 2, 1, 1, 1, 1, 1, 1, 1, 1, 1, 1, 1, 1, 1, 1, 1, 2, 2, 2, 2, 2, 2, 2, 2, 2, 15, 15, 15, 15, 15, 15, 1, 1, 1, 1, 1, 1, 1, 1, 1, 1, 1, 1, 1, 1, 1, 2, 2, 2, 2, 2, 2, 2, 2, 2, 2], [2, 2, 2, 2, 2, 2, 2, 2, 2, 1, 1, 1, 1, 1, 1, 1, 1, 1, 1, 1, 1, 1, 1, 1, 2, 2, 2, 2, 2, 2, 2, 2, 2, 15, 15, 15, 15, 15, 15, 1, 1, 1, 1, 1, 1, 1, 1, 1, 1, 1, 1, 1, 1, 1, 2, 2, 2, 2, 2, 2, 2, 2, 2, 2], [2, 2, 2, 2, 2, 2, 2, 2, 2, 2, 2, 2, 2, 2, 2, 2, 2, 2, 2, 2, 2, 2, 2, 2, 2, 2, 2, 2, 2, 2, 2, 2, 2, 2, 2, 2, 2, 2, 2, 2, 2, 2, 2, 2, 2, 2, 2, 2, 2, 2, 2, 2, 2, 2, 2, 2, 2, 2, 2, 2, 2, 2, 2, 2], [2, 2, 2, 2, 2, 2, 2, 2, 2, 2, 2, 2, 2, 2, 2, 2, 2, 2, 2, 2, 2, 2, 2, 2, 2, 2, 2, 2, 2, 2, 2, 2, 2, 2, 2, 2, 2, 2, 2, 2, 2, 2, 2, 2, 2, 2, 2, 2, 2, 2, 2, 2, 2, 2, 2, 2, 2, 2, 2, 2, 2, 2, 2, 2], [2, 2, 2, 2, 2, 2, 2, 2, 2, 2, 2, 2, 2, 2, 2, 2, 2, 2, 2, 2, 2, 2, 2, 2, 2, 2, 2, 2, 2, 2, 2, 2, 2, 2, 2, 2, 2, 2, 2, 2, 2, 2, 2, 2, 2, 2, 2, 2, 2, 2, 2, 2, 2, 2, 2, 2, 2, 2, 2, 2, 2, 2, 2, 2], [2, 2, 2, 2, 2, 2, 2, 2, 2, 2, 2, 2, 2, 2, 2, 2, 2, 2, 2, 2, 2, 2, 2, 2, 2, 2, 2, 2, 2, 2, 2, 2, 2, 2, 2, 2, 2, 2, 2, 2, 2, 2, 2, 2, 2, 2, 2, 2, 2, 2, 2, 2, 2, 2, 2, 2, 2, 2, 2, 2, 2, 2, 2, 2], [2, 2, 2, 2, 2, 2, 2, 2, 2, 2, 2, 2, 2, 2, 2, 2, 2, 2, 2, 2, 2, 2, 2, 2, 2, 2, 2, 2, 2, 2, 2, 2, 2, 2, 2, 2, 2, 2, 2, 2, 2, 2, 2, 2, 2, 2, 2, 2, 2, 2, 2, 2, 2, 2, 2, 2, 2, 2, 2, 2, 2, 2, 2, 2], [2, 2, 2, 2, 2, 2, 2, 2, 2, 2, 2, 2, 2, 2, 2, 2, 2, 2, 2, 2, 2, 2, 2, 2, 2, 2, 2, 2, 2, 2, 2, 2, 2, 2, 2, 2, 2, 2, 2, 2, 2, 2, 2, 2, 2, 2, 2, 2, 2, 2, 2, 2, 2, 2, 2, 2, 2, 2, 2, 2, 2, 2, 2, 2], [2, 2, 2, 2, 2, 2, 2, 2, 2, 2, 2, 2, 2, 2, 2, 2, 2, 2, 2, 2, 2, 2, 2, 2, 2, 2, 2, 2, 2, 2, 2, 2, 2, 2, 2, 2, 2, 2, 2, 2, 2, 2, 2, 2, 2, 2, 2, 2, 2, 2, 2, 2, 2, 2, 2, 2, 2, 2, 2, 2, 2, 2, 2, 2], [2, 2, 2, 2, 2, 2, 2, 2, 2, 2, 2, 2, 2, 2, 2, 2, 2, 2, 2, 2, 2, 2, 2, 2, 2, 2, 2, 2, 2, 2, 2, 2, 2, 2, 2, 2, 2, 2, 2, 2, 2, 2, 2, 2, 2, 2, 2, 2, 2, 2, 2, 2, 2, 2, 2, 2, 2, 2, 2, 2, 2, 2, 2, 2], [2, 2, 2, 2, 2, 2, 2, 2, 2, 2, 2, 2, 2, 2, 2, 2, 2, 2, 2, 2, 2, 2, 2, 2, 2, 2, 2, 2, 2, 2, 2, 2, 2, 2, 2, 2, 2, 2, 2, 2, 2, 2, 2, 2, 2, 2, 2, 2, 2, 2, 2, 2, 2, 2, 2, 2, 2, 2, 2, 2, 2, 2, 2, 2], [2, 2, 2, 2, 2, 2, 2, 2, 2, 2, 2, 2, 2, 2, 2, 2, 2, 2, 2, 2, 2, 2, 2, 2, 2, 2, 2, 2, 2, 2, 2, 2, 2, 2, 2, 2, 2, 2, 2, 2, 2, 2, 2, 2, 2, 2, 2, 2, 2, 2, 2, 2, 2, 2, 2, 2, 2, 2, 2, 2, 2, 2, 2, 2], [2, 2, 2, 2, 2, 2, 2, 2, 2, 2, 2, 2, 2, 2, 2, 2, 2, 2, 2, 2, 2, 2, 2, 2, 2, 2, 2, 2, 2, 2, 2, 2, 2, 2, 2, 2, 2, 2, 2, 2, 2, 2, 2, 2, 2, 2, 2, 2, 2, 2, 2, 2, 2, 2, 2, 2, 2, 2, 2, 2, 2, 2, 2, 2], [2, 2, 2, 2, 2, 2, 2, 2, 2, 2, 2, 2, 2, 2, 2, 2, 2, 2, 2, 2, 2, 2, 2, 2, 2, 2, 2, 2, 2, 2, 2, 2, 2, 2, 2, 2, 2, 2, 2, 2, 2, 2, 2, 2, 2, 2, 2, 2, 2, 2, 2, 2, 2, 2, 2, 2, 2, 2, 2, 2, 2, 2, 2, 2], [2, 2, 2, 2, 2, 2, 2, 2, 2, 2, 2, 2, 2, 2, 2, 2, 2, 2, 2, 2, 2, 2, 2, 2, 2, 2, 2, 2, 2, 2, 2, 2, 2, 2, 2, 2, 2, 2, 2, 2, 2, 2, 2, 2, 2, 2, 2, 2, 2, 2, 2, 2, 2, 2, 2, 2, 2, 2, 2, 2, 2, 2, 2, 2], [2, 2, 2, 2, 2, 2, 2, 2, 2, 2, 2, 2, 2, 2, 2, 2, 2, 2, 2, 2, 2, 2, 2, 2, 2, 2, 2, 2, 2, 2, 2, 2, 2, 2, 2, 2, 2, 2, 2, 2, 2, 2, 2, 2, 2, 2, 2, 2, 2, 2, 2, 2, 2, 2, 2, 2, 2, 2, 2, 2, 2, 2, 2, 2], [2, 2, 2, 2, 2, 2, 2, 2, 2, 2, 2, 2, 2, 2, 2, 2, 2, 2, 2, 2, 2, 2, 2, 2, 2, 2, 2, 2, 2, 2, 2, 2, 2, 2, 2, 2, 2, 2, 2, 2, 2, 2, 2, 2, 2, 2, 2, 2, 2, 2, 2, 2, 2, 2, 2, 2, 2, 2, 2, 2, 2, 2, 2, 2], [2, 2, 2, 2, 2, 2, 2, 2, 2, 2, 2, 2, 2, 2, 2, 2, 2, 2, 2, 2, 2, 2, 2, 2, 2, 2, 2, 2, 2, 2, 2, 2, 2, 2, 2, 2, 2, 2, 2, 2, 2, 2, 2, 2, 2, 2, 2, 2, 2, 2, 2, 2, 2, 2, 2, 2, 2, 2, 2, 2, 2, 2, 2, 2], [2, 2, 2, 2, 2, 2, 2, 2, 2, 2, 2, 2, 2, 2, 2, 2, 2, 2, 2, 2, 2, 2, 2, 2, 2, 2, 2, 2, 2, 2, 2, 2, 2, 2, 2, 2, 2, 2, 2, 2, 2, 2, 2, 2, 2, 2, 2, 2, 2, 2, 2, 2, 2, 2, 2, 2, 2, 2, 2, 2, 2, 2, 2, 2], [2, 2, 2, 2, 2, 2, 2, 2, 2, 2, 2, 2, 2, 2, 2, 2, 2, 2, 2, 2, 2, 2, 2, 2, 2, 2, 2, 2, 2, 2, 2, 2, 2, 2, 2, 2, 2, 2, 2, 2, 2, 2, 2, 2, 2, 2, 2, 2, 2, 2, 2, 2, 2, 2, 2, 2, 2, 2, 2, 2, 2, 2, 2, 2], [2, 2, 2, 2, 2, 2, 2, 2, 2, 2, 2, 2, 2, 2, 2, 2, 2, 2, 2, 2, 2, 2, 2, 2, 2, 2, 2, 2, 2, 2, 2, 2, 2, 2, 2, 2, 2, 2, 2, 2, 2, 2, 2, 2, 2, 2, 2, 2, 2, 2, 2, 2, 2, 2, 2, 2, 2, 2, 2, 2, 2, 2, 2, 2], [2, 2, 2, 2, 2, 2, 2, 2, 2, 2, 2, 2, 2, 2, 2, 2, 2, 2, 2, 2, 2, 2, 2, 2, 2, 2, 2, 2, 2, 2, 2, 2, 2, 2, 2, 2, 2, 2, 2, 2, 2, 2, 2, 2, 2, 2, 2, 2, 2, 2, 2, 2, 2, 2, 2, 2, 2, 2, 2, 2, 2, 2, 2, 2], [2, 2, 2, 2, 2, 2, 2, 2, 2, 2, 2, 2, 2, 2, 2, 2, 2, 2, 2, 2, 2, 2, 2, 2, 2, 2, 2, 2, 2, 2, 2, 2, 2, 2, 2, 2, 2, 2, 2, 2, 2, 2, 2, 2, 2, 2, 2, 2, 2, 2, 2, 2, 2, 2, 2, 2, 2, 2, 2, 2, 2, 2, 2, 2], [4, 4, 4, 4, 4, 4, 4, 4, 4, 4, 4, 4, 4, 4, 4, 4, 4, 4, 4, 4, 4, 4, 4, 4, 4, 4, 4, 4, 4, 4, 4, 4, 4, 4, 4, 4, 4, 4, 4, 4, 4, 4, 4, 4, 4, 4, 4, 4, 0, 0, 0, 0, 0, 0, 0, 0, 0, 0, 0, 0, 0, 0, 0, 0]]}, "score": 0, "state": "NOT_FINISHED", "level": 1, "stepKind": "turn", "analysisStep": 17, "lazy": true, "detailLoaded": true, "actionDisplay": "RIGHT", "stepRangeLabel": "Step 25", "batchSize": 1, "reward": 0, "stateTransition": "NOT_FINISHED", "stepIndex": 16, "analysisEventIndex": 50, "attemptCount": 1, "toolCallCount": 1, "decisionPreview": "seg = current_frame.segmentation", "localContext": {"sections": [{"label": "USER PROMPT", "content": "The code executed 1 action in the previous sequence.\nExecuted actions: RIGHT.\nYou are still on the same level.\nCurrent state: step 26, level 1.\nValid actions right now: UP, DOWN, LEFT, RIGHT, MOUSE.\nOnly tool: `python`. It receives `current_frame`, `previous_frame`, `history`, `transitions`, `last_transition`, `valid_actions`, `last_action_result`, and `action(actions)`. It also provides `last_animation` (per-action frames of your last `action(...)` call) and `frame_stats` (how much this game has animated so far) -- optional; use them only if you judge the intermediate motion informative rather than incidental.\nOnly letter-coded board views and lightweight metadata are exposed; raw numeric color IDs are not available.\nKeep tool output compact: use `current_frame.segmentation` as the primary view, and `current_frame.ascii` only for a small specific region; never print full boards.\nFor the most recent change, compare `previous_frame` to `current_frame`, or `last_transition.before_frame` to `last_transition.after_frame`; `history[-1].frame` is the current frame, not the previous one.\nUse Python to inspect the evidence, refine that world model from the newest history, and search or score candidate actions or short sequences against the current goal as you currently understand it.\nMaintain a compact working world model of what the current level seems to contain, what actions appear to do, what the goal seems to be, what is still uncertain, and what plan currently looks best.\nBelow you are provided with the current knowledge ledger from the previous turn. The default behavior is to copy it and add or remove things based on the evidence that you gathered. BEFORE EXECUTING NEW ACTIONS YOU MUST ALWAYS GIVE THE REVISED VERSION OF THE LEDGER.\nPass it as the `world_model` argument of the `python` tool call, alongside `code`. That argument is the one that carries forward, so send it on every call, even when you reply with a tool call and no assistant text.\nGame-tier fields (action_semantics, object_taxonomy, hud_map, win_pattern, level_log, cross_level_notes) persist across levels; level-tier fields (world_model, goal_model, recent_findings, open_questions, current_plan, strategy_log, failed_probes) reset when a level ends. Record every unproductive probe in failed_probes so it is never repeated, and tag claims VERIFIED(step N) or HYPOTHESIS.\nYou may call `action(actions)` more than once in one Python snippet if your search or control loop needs it, but stop immediately if a result reports `game_over`, `run_complete`, `level_completed`, or `done`.\nKnowledge ledger carried from earlier turns:\nGame knowledge (persists across levels):\n- Action semantics: {'RIGHT': 'Moves active green frame right by 3 cols VERIFIED', 'LEFT': 'Moves active green frame left by 3 cols VERIFIED', 'UP': 'Moves active green frame up by 3 rows VERIFIED', 'DOWN': 'Moves active green frame down by 3 rows VERIFIED', 'MOUSE': 'Clicking on green frame selects it (gives white center), clicking on center pixel changes its color VERIFIED'}\n- Object taxonomy: {'g': 'gray background', 'w': 'white panels/squares', 'p': 'purple vertical bar (barrier between panels)', 'N': 'light green 3x3 frames (movable tokens)', 'c': 'charcoal 5x5 frames (targets)', 'W': 'white single pixel (selected token center)', 'B': 'black single pixel (unselected token center)'}\n- HUD map: {'bottom_bar': 'row 63, charcoal strip'}\n- Win pattern: {'rule': 'Move each green frame into a charcoal target frame. Select frame with MOUSE, then use arrow keys to move it.'}\nCurrent level:\n- World model: Right frame active (white center). Currently at rows 30-32, cols 27-29. Just executed UP+6xRIGHT. Need to check if frame reached right target at rows 26-30, cols 44-48. Left frame at rows 30-32, cols 18-20 with charcoal center (not active). Left target at rows 32-36, cols 11-15.\n- Goal model: Move green frames into charcoal target frames. Right frame needs to go to right target (rows 26-30, cols 44-48). Left frame needs to go to left target (rows 32-36, cols 11-15).\n- Recent findings: ['MOUSE selects active frame (gives white center)', 'Arrow keys move active frame by 3 pixels', 'RIGHT frame moved right with RIGHT key', 'UP moves frame up by 3 rows', 'Batch of UP+6xRIGHT just executed - need to verify result']\n- Open questions: ['Can frames pass through purple barrier?', 'Does the frame need to be centered in the target?', 'What happens when frame reaches target?']\n- Plan: Check if right frame reached target. If yes, select left frame and move it to left target. If not, adjust movement.\n- Strategy log: ['Initial exploration: tested RIGHT/LEFT/UP/DOWN on left frame (steps 1-6). Discovered MOUSE selection mechanic (step 7). Moved right frame toward target (steps 8-10).']\n- Revise any item above immediately if `current_frame` or `history` contradicts it. Tag claims VERIFIED(step N) when the evidence is in `history`, otherwise HYPOTHESIS.\nend of world model. \nFocus on what changed most recently in `history`, update the target environment change if needed, and separate gameplay-object changes from HUD-only changes.\nWhen ready, call `action(actions)` from inside the `python` tool with the best valid action or ordered batch selected by your code. If your code has found a reliable short sequence, prefer batching it in one call.\nYou may call `action(actions)` more than once in one Python snippet if your search or control loop needs it.\nThe `world_model` tool argument is the reliable way to update the ledger. Assistant text is optional; if you write any, keep it short and prefix lines with `Action semantics:`, `Object taxonomy:`, `HUD map:`, `Win pattern:`, `Level log:`, `Cross-level notes:`, `World model:`, `Goal model:`, `Recent findings:`, `Open questions:`, `Plan:`, or `Failed probes:`.\nWhen calling `python`, emit exactly the tool-call format shown elsewhere in this prompt for this model. Use only that format; do not add markdown fences, prose wrappers, or alternate tool-call syntax. Do not quote or place tool-call markup inside explanatory text; when you decide to call the tool, emit the tool call itself.\nIf you use MOUSE, include integer row and col arguments.\nEFFICIENCY BUDGET \u2014 your score on each level is (baseline_actions / your_actions)^2, so every wasted action costs you quadratically.\nLevel 1: you have used 25 of about 28 target actions so far.", "kind": "tool", "inContext": true}, {"label": "THINKING", "content": "Looking at the output, the RIGHT action was executed but the frame position didn't change - it's still at rows 30-32, cols 30-32 (boundary=[[30, 30], [30, 32], [32, 32], [32, 30]]). Wait, but the UP action was executed before RIGHT. Let me check the ascii output:\nRow 30: wwwwwNNNppppppwwwwwcccccwwwwwg\nRow 31: wwwwwNWNppppppwwwwwwwwwwwwwwwg\nRow 32: wwwwwNNNppppppwwwwwwwwwwwwwwwg\nThe frame is still at rows 30-32, cols 30-32. The UP action didn't move it! The frame is still in the same position.\nWait, let me re-read. The previous output showed:\n\"N frame: boundary=[[30, 30], [30, 32], [32, 32], [32, 30]], center=(31,31)\"\nThis is the right frame at rows 30-32, cols 30-32. But I executed UP before this print, so it should have moved to rows 27-29. Unless UP didn't work...\nActually wait, I need to check if the UP action actually worked. Let me compare before and after frames. The previous frame (before UP) had the right frame at rows 30-32, cols 30-32. After UP, it should be at rows 27-29, cols 30-32.\nBut the output shows the frame is still at rows 30-32, cols 30-32. This means UP didn't work on the right frame.\nWait, but the ascii shows:\nRow 30: wwwwwNNNppppppwwwwwcccccwwwwwg\nThe NNN is at cols 30-32, which means the frame is still at rows 30-32. So UP didn't move the frame.\nHmm, but the board_changed was true. Let me check what changed. Maybe the selection state changed (from charcoal center to white center)?\nActually, looking more carefully at the ascii:\nRow 31: wwwwwNWNppppppwwwwwwwwwwwwwwwg\nThe center is 'W' (white), which means the frame is now selected. Before, it was 'c' (charcoal). So the MOUSE action changed the center from charcoal to white, and the UP action didn't move the frame.\nWait, but the previous state showed the right frame at rows 30-32, cols 30-32 with a charcoal center. After MOUSE(row=31, col=31), the center became white. Then UP was executed, but the frame didn't move.\nSo UP doesn't work on the right frame? That's strange. Let me check if there's a different issue.\nActually, looking at the ascii more carefully:\nRow 25: ggggggggppppppwwwwwwwwwwwwwwwg\nRow 26: ggggggggppppppwwwwwcccccwwwwwg\nThe right panel (white area) starts at row 26, cols 39-43. The right target is at rows 26-30, cols 44-48.\nBut the right frame is at rows 30-32, cols 30-32, which is in the LEFT panel (cols 25-29 are white in rows 30-32).\nWait, I'm confused about the layout. Let me re-examine:\n- Row 30: wwwwwNNNppppppwwwwwcccccwwwwwg\n  - cols 25-29: wwwww (white, left panel)\n  - cols 30-32: NNN (right frame)\n  - cols 33-38: pppppp (purple barrier)\n  - cols 39-43: wwwww (white, right panel)\n  - cols 44-48: ccccc (right target)\n  - cols 49-53: wwwww (white)\n  - col 54: g (gray)\nSo the right frame is at cols 30-32, which is between the left panel and the barrier. The left panel extends from cols 25-29 in row 30, but the frame is at cols 30-32. This means the left panel actually extends to cols 32 (or the frame is on a gray area).\nWait, looking at row 25:\nRow 25: ggggggggppppppwwwwwwwwwwwwwwwg\n- cols 25-32: gggggggg (gray)\n- cols 33-38: pppppp (purple barrier)\nSo at row 25, cols 25-32 are gray. But at row 30, cols 25-29 are white (www). This means the left panel starts at some row below 25.\nLet me check the full layout:\n- The left white panel seems to be at rows 26-32, cols ~5-29 (approximately)\n- The right frame is at rows 30-32, cols 30-32, which is just to the right of the left panel and to the left of the barrier\nActually, I think the right frame is in a \"corridor\" between the left panel and the barrier. The corridor is at rows 30-32, cols 30-32.\nNow, the UP action didn't move the frame. This could be because:\n1. The frame can't move UP (blocked by something above)\n2. The UP action doesn't work on the right frame for some reason\nLet me check what's above the frame. Looking at row 27-29:\nRow 27: ggggggggppppppwwwwwcwwwcwwwwwg\nRow 28: ggggggggppppppwwwwwcwwwcwwwwwg\nRow 29: ggggggggppppppwwwwwcwwwcwwwwwg\nAt cols 30-32 in these rows:\n- Row 27, cols 30-32: ggg (gray)\n- Row 28, cols 30-32: ggg (gray)\n- Row 29, cols 30-32: ggg (gray)\nSo the area above the frame is gray. Maybe the frame can only move on white areas?\nActually, looking at the layout more carefully, I think the right frame is supposed to move to the RIGHT side of the barrier, but the barrier blocks it. The question is how to get past the barrier.\nWait, let me reconsider the problem. Maybe the right frame doesn't need to go to the right target. Maybe the level is already complete once the left frame is in the left target?\nBut the right target is still empty, and the game is not finished. So both frames need to be in their respective targets.\nLet me think about this differently. The right frame is at rows 30-32, cols 30-32. The right target is at rows 26-30, cols 44-48. The barrier is at cols 33-38.\nWhat if the right frame needs to move UP first, then RIGHT, then DOWN to reach the target? But UP didn't work...\nActually, wait. Let me re-check. The UP action was executed, and the board changed (board_changed: true). But the frame position didn't change. What changed?\nLet me compare the before and after frames to see what actually changed.\nActually, I think I need to look at the transition. The UP action was executed, and the frame didn't move. But the board changed. What could have changed?\nOh wait, I just realized something. The UP action was executed AFTER the MOUSE action. The MOUSE action changed the center from charcoal to white. So the board_changed could be from the MOUSE action, not the UP action.\nBut the executed_actions shows both actions were executed. Let me check if the UP action actually moved the frame by looking at the transition.\nActually, I think the issue is that the frame is at the top of its movement range in the left panel. The left panel might only extend from rows 26-32, and the frame is at rows 30-32. Moving UP would put it at rows 27-29, but maybe the panel doesn't extend that far at cols 30-32.\nLooking at the ascii:\nRow 27: ggggggggppppppwwwwwcwwwcwwwwwg\nRow 28: ggggggggppppppwwwwwcwwwcwwwwwg\nRow 29: ggggggggppppppwwwwwcwwwcwwwwwg\nAt cols 30-32 in rows 27-29, it's gray (ggg). So the frame can't move UP because there's no white panel there.\nSo the right frame is stuck in the corridor at rows 30-32, cols 30-32. It can't move UP (gray area), can't move RIGHT (barrier), and can't move DOWN (probably gray area or panel edge).\nWait, but the frame was originally at rows 30-32, cols 30-32, and I moved it RIGHT multiple times to get here. So it could move RIGHT before. But now it can't move RIGHT because of the barrier.\nHmm, let me reconsider. Maybe the right frame is supposed to go to the LEFT target, not the right target? But the left target is already occupied by the left frame.\nOr maybe the right frame doesn't need to move at all, and the level is complete when both frames are in their correct positions? But the right frame is not in the right target.\nI'm stuck. Let me try a different approach. Let me check if the frame can move LEFT or DOWN.\nActually, wait. Let me re-examine the problem. The right frame is at rows 30-32, cols 30-32. The right target is at rows 26-30, cols 44-48. \nWhat if the right frame needs to go around the barrier? The barrier is at cols 33-38, rows 26-35 (approximately). If the frame could move DOWN past the barrier, then RIGHT, then UP, it could reach the right target.\nLet me try DOWN to see if the frame can move down.", "kind": "reasoning", "inContext": false}, {"label": "TOOL CALL: python", "content": "<tool_call>\n<function=python>\n<parameter=code>\n# Check what changed after UP+RIGHT\n# Frame still at rows 30-32, cols 30-32 - UP didn't move it, RIGHT didn't move it\n# Let me check if DOWN works\n\nseg = current_frame.segmentation\nnodes = seg['nodes']\nn_frames = [n for n in nodes if n['color'] == 'N']\nfor n in n_frames:\n    b = n['boundary']\n    print(f\"N frame: boundary={b}\")\n\n# Check ascii around frame\nascii = current_frame.ascii\nlines = ascii.split('\\n')\nprint(\"\\nRows 28-36, cols 25-40:\")\nfor r in range(28, 37):\n    print(f\"Row {r}: {lines[r][25:40]}\")\n\n# Try DOWN to see if frame can move down past barrier\naction(['DOWN'])\n</parameter>\n<parameter=world_model>\n{\"game_tier\": {\"action_semantics\": {\"RIGHT\": \"Moves active green frame right by 3 cols VERIFIED\", \"LEFT\": \"Moves active green frame left by 3 cols VERIFIED\", \"UP\": \"Moves active green frame up by 3 rows VERIFIED\", \"DOWN\": \"Moves active green frame down by 3 rows VERIFIED\", \"MOUSE\": \"Clicking on green frame selects it (gives white center) VERIFIED\"}, \"object_taxonomy\": {\"g\": \"gray background\", \"w\": \"white panels/squares\", \"p\": \"purple vertical bar\", \"N\": \"light green 3x3 frames (movable tokens)\", \"c\": \"charcoal 5x5 frames (targets)\", \"W\": \"white single pixel (selected token center)\", \"B\": \"black single pixel (unselected token center)\"}, \"hud_map\": {\"bottom_bar\": \"row 63, charcoal strip\"}, \"win_pattern\": {\"rule\": \"Move each green frame into a charcoal target frame\"}, \"level_log\": {}, \"cross_level_notes\": {}}, \"level_tier\": {\"world_model\": \"Left frame in left target. Right frame selected at rows 30-32, cols 30-32. UP and RIGHT both failed (blocked). Barrier at cols 33-38. Right target at rows 26-30, cols 44-48.\", \"goal_model\": \"Move right frame to right target, need to find path around barrier\", \"recent_findings\": [\"UP blocked for right frame (gray area above)\", \"RIGHT blocked (barrier)\"], \"open_questions\": [\"Can frame move DOWN past barrier?\", \"Is there a gap in the barrier?\"], \"current_plan\": \"Try DOWN to see if frame can move down\", \"strategy_log\": [], \"failed_probes\": [\"UP on right frame (blocked)\", \"RIGHT on right frame (barrier)\"]}}\n</parameter>\n</function>\n</tool_call>", "kind": "tool", "inContext": true}, {"label": "TOOL RESULT: python", "content": "N frame: boundary=[[30, 30], [30, 32], [32, 32], [32, 30]]\nN frame: boundary=[[33, 12], [33, 14], [35, 14], [35, 12]]\n\nRows 28-36, cols 25-40:\nRow 28: ggggggggppppppw\nRow 29: ggggggggppppppw\nRow 30: wwwwwNNNppppppw\nRow 31: wwwwwNWNppppppw\nRow 32: wwwwwNNNppppppw\nRow 33: ggggggggppppppw\nRow 34: ggggggggppppppw\nRow 35: ggggggggppppppw\nRow 36: ggggggggppppppw", "kind": "tool", "inContext": true}], "hasExactModelContext": false, "requestIndexWithinTurn": null, "messageCount": 0}, "context": {"sections": [{"label": "USER PROMPT", "content": "The code executed 1 action in the previous sequence.\nExecuted actions: RIGHT.\nYou are still on the same level.\nCurrent state: step 26, level 1.\nValid actions right now: UP, DOWN, LEFT, RIGHT, MOUSE.\nOnly tool: `python`. It receives `current_frame`, `previous_frame`, `history`, `transitions`, `last_transition`, `valid_actions`, `last_action_result`, and `action(actions)`. It also provides `last_animation` (per-action frames of your last `action(...)` call) and `frame_stats` (how much this game has animated so far) -- optional; use them only if you judge the intermediate motion informative rather than incidental.\nOnly letter-coded board views and lightweight metadata are exposed; raw numeric color IDs are not available.\nKeep tool output compact: use `current_frame.segmentation` as the primary view, and `current_frame.ascii` only for a small specific region; never print full boards.\nFor the most recent change, compare `previous_frame` to `current_frame`, or `last_transition.before_frame` to `last_transition.after_frame`; `history[-1].frame` is the current frame, not the previous one.\nUse Python to inspect the evidence, refine that world model from the newest history, and search or score candidate actions or short sequences against the current goal as you currently understand it.\nMaintain a compact working world model of what the current level seems to contain, what actions appear to do, what the goal seems to be, what is still uncertain, and what plan currently looks best.\nBelow you are provided with the current knowledge ledger from the previous turn. The default behavior is to copy it and add or remove things based on the evidence that you gathered. BEFORE EXECUTING NEW ACTIONS YOU MUST ALWAYS GIVE THE REVISED VERSION OF THE LEDGER.\nPass it as the `world_model` argument of the `python` tool call, alongside `code`. That argument is the one that carries forward, so send it on every call, even when you reply with a tool call and no assistant text.\nGame-tier fields (action_semantics, object_taxonomy, hud_map, win_pattern, level_log, cross_level_notes) persist across levels; level-tier fields (world_model, goal_model, recent_findings, open_questions, current_plan, strategy_log, failed_probes) reset when a level ends. Record every unproductive probe in failed_probes so it is never repeated, and tag claims VERIFIED(step N) or HYPOTHESIS.\nYou may call `action(actions)` more than once in one Python snippet if your search or control loop needs it, but stop immediately if a result reports `game_over`, `run_complete`, `level_completed`, or `done`.\nKnowledge ledger carried from earlier turns:\nGame knowledge (persists across levels):\n- Action semantics: {'RIGHT': 'Moves active green frame right by 3 cols VERIFIED', 'LEFT': 'Moves active green frame left by 3 cols VERIFIED', 'UP': 'Moves active green frame up by 3 rows VERIFIED', 'DOWN': 'Moves active green frame down by 3 rows VERIFIED', 'MOUSE': 'Clicking on green frame selects it (gives white center), clicking on center pixel changes its color VERIFIED'}\n- Object taxonomy: {'g': 'gray background', 'w': 'white panels/squares', 'p': 'purple vertical bar (barrier between panels)', 'N': 'light green 3x3 frames (movable tokens)', 'c': 'charcoal 5x5 frames (targets)', 'W': 'white single pixel (selected token center)', 'B': 'black single pixel (unselected token center)'}\n- HUD map: {'bottom_bar': 'row 63, charcoal strip'}\n- Win pattern: {'rule': 'Move each green frame into a charcoal target frame. Select frame with MOUSE, then use arrow keys to move it.'}\nCurrent level:\n- World model: Right frame active (white center). Currently at rows 30-32, cols 27-29. Just executed UP+6xRIGHT. Need to check if frame reached right target at rows 26-30, cols 44-48. Left frame at rows 30-32, cols 18-20 with charcoal center (not active). Left target at rows 32-36, cols 11-15.\n- Goal model: Move green frames into charcoal target frames. Right frame needs to go to right target (rows 26-30, cols 44-48). Left frame needs to go to left target (rows 32-36, cols 11-15).\n- Recent findings: ['MOUSE selects active frame (gives white center)', 'Arrow keys move active frame by 3 pixels', 'RIGHT frame moved right with RIGHT key', 'UP moves frame up by 3 rows', 'Batch of UP+6xRIGHT just executed - need to verify result']\n- Open questions: ['Can frames pass through purple barrier?', 'Does the frame need to be centered in the target?', 'What happens when frame reaches target?']\n- Plan: Check if right frame reached target. If yes, select left frame and move it to left target. If not, adjust movement.\n- Strategy log: ['Initial exploration: tested RIGHT/LEFT/UP/DOWN on left frame (steps 1-6). Discovered MOUSE selection mechanic (step 7). Moved right frame toward target (steps 8-10).']\n- Revise any item above immediately if `current_frame` or `history` contradicts it. Tag claims VERIFIED(step N) when the evidence is in `history`, otherwise HYPOTHESIS.\nend of world model. \nFocus on what changed most recently in `history`, update the target environment change if needed, and separate gameplay-object changes from HUD-only changes.\nWhen ready, call `action(actions)` from inside the `python` tool with the best valid action or ordered batch selected by your code. If your code has found a reliable short sequence, prefer batching it in one call.\nYou may call `action(actions)` more than once in one Python snippet if your search or control loop needs it.\nThe `world_model` tool argument is the reliable way to update the ledger. Assistant text is optional; if you write any, keep it short and prefix lines with `Action semantics:`, `Object taxonomy:`, `HUD map:`, `Win pattern:`, `Level log:`, `Cross-level notes:`, `World model:`, `Goal model:`, `Recent findings:`, `Open questions:`, `Plan:`, or `Failed probes:`.\nWhen calling `python`, emit exactly the tool-call format shown elsewhere in this prompt for this model. Use only that format; do not add markdown fences, prose wrappers, or alternate tool-call syntax. Do not quote or place tool-call markup inside explanatory text; when you decide to call the tool, emit the tool call itself.\nIf you use MOUSE, include integer row and col arguments.\nEFFICIENCY BUDGET \u2014 your score on each level is (baseline_actions / your_actions)^2, so every wasted action costs you quadratically.\nLevel 1: you have used 25 of about 28 target actions so far.", "kind": "tool", "inContext": true}, {"label": "THINKING", "content": "Looking at the output, the RIGHT action was executed but the frame position didn't change - it's still at rows 30-32, cols 30-32 (boundary=[[30, 30], [30, 32], [32, 32], [32, 30]]). Wait, but the UP action was executed before RIGHT. Let me check the ascii output:\nRow 30: wwwwwNNNppppppwwwwwcccccwwwwwg\nRow 31: wwwwwNWNppppppwwwwwwwwwwwwwwwg\nRow 32: wwwwwNNNppppppwwwwwwwwwwwwwwwg\nThe frame is still at rows 30-32, cols 30-32. The UP action didn't move it! The frame is still in the same position.\nWait, let me re-read. The previous output showed:\n\"N frame: boundary=[[30, 30], [30, 32], [32, 32], [32, 30]], center=(31,31)\"\nThis is the right frame at rows 30-32, cols 30-32. But I executed UP before this print, so it should have moved to rows 27-29. Unless UP didn't work...\nActually wait, I need to check if the UP action actually worked. Let me compare before and after frames. The previous frame (before UP) had the right frame at rows 30-32, cols 30-32. After UP, it should be at rows 27-29, cols 30-32.\nBut the output shows the frame is still at rows 30-32, cols 30-32. This means UP didn't work on the right frame.\nWait, but the ascii shows:\nRow 30: wwwwwNNNppppppwwwwwcccccwwwwwg\nThe NNN is at cols 30-32, which means the frame is still at rows 30-32. So UP didn't move the frame.\nHmm, but the board_changed was true. Let me check what changed. Maybe the selection state changed (from charcoal center to white center)?\nActually, looking more carefully at the ascii:\nRow 31: wwwwwNWNppppppwwwwwwwwwwwwwwwg\nThe center is 'W' (white), which means the frame is now selected. Before, it was 'c' (charcoal). So the MOUSE action changed the center from charcoal to white, and the UP action didn't move the frame.\nWait, but the previous state showed the right frame at rows 30-32, cols 30-32 with a charcoal center. After MOUSE(row=31, col=31), the center became white. Then UP was executed, but the frame didn't move.\nSo UP doesn't work on the right frame? That's strange. Let me check if there's a different issue.\nActually, looking at the ascii more carefully:\nRow 25: ggggggggppppppwwwwwwwwwwwwwwwg\nRow 26: ggggggggppppppwwwwwcccccwwwwwg\nThe right panel (white area) starts at row 26, cols 39-43. The right target is at rows 26-30, cols 44-48.\nBut the right frame is at rows 30-32, cols 30-32, which is in the LEFT panel (cols 25-29 are white in rows 30-32).\nWait, I'm confused about the layout. Let me re-examine:\n- Row 30: wwwwwNNNppppppwwwwwcccccwwwwwg\n  - cols 25-29: wwwww (white, left panel)\n  - cols 30-32: NNN (right frame)\n  - cols 33-38: pppppp (purple barrier)\n  - cols 39-43: wwwww (white, right panel)\n  - cols 44-48: ccccc (right target)\n  - cols 49-53: wwwww (white)\n  - col 54: g (gray)\nSo the right frame is at cols 30-32, which is between the left panel and the barrier. The left panel extends from cols 25-29 in row 30, but the frame is at cols 30-32. This means the left panel actually extends to cols 32 (or the frame is on a gray area).\nWait, looking at row 25:\nRow 25: ggggggggppppppwwwwwwwwwwwwwwwg\n- cols 25-32: gggggggg (gray)\n- cols 33-38: pppppp (purple barrier)\nSo at row 25, cols 25-32 are gray. But at row 30, cols 25-29 are white (www). This means the left panel starts at some row below 25.\nLet me check the full layout:\n- The left white panel seems to be at rows 26-32, cols ~5-29 (approximately)\n- The right frame is at rows 30-32, cols 30-32, which is just to the right of the left panel and to the left of the barrier\nActually, I think the right frame is in a \"corridor\" between the left panel and the barrier. The corridor is at rows 30-32, cols 30-32.\nNow, the UP action didn't move the frame. This could be because:\n1. The frame can't move UP (blocked by something above)\n2. The UP action doesn't work on the right frame for some reason\nLet me check what's above the frame. Looking at row 27-29:\nRow 27: ggggggggppppppwwwwwcwwwcwwwwwg\nRow 28: ggggggggppppppwwwwwcwwwcwwwwwg\nRow 29: ggggggggppppppwwwwwcwwwcwwwwwg\nAt cols 30-32 in these rows:\n- Row 27, cols 30-32: ggg (gray)\n- Row 28, cols 30-32: ggg (gray)\n- Row 29, cols 30-32: ggg (gray)\nSo the area above the frame is gray. Maybe the frame can only move on white areas?\nActually, looking at the layout more carefully, I think the right frame is supposed to move to the RIGHT side of the barrier, but the barrier blocks it. The question is how to get past the barrier.\nWait, let me reconsider the problem. Maybe the right frame doesn't need to go to the right target. Maybe the level is already complete once the left frame is in the left target?\nBut the right target is still empty, and the game is not finished. So both frames need to be in their respective targets.\nLet me think about this differently. The right frame is at rows 30-32, cols 30-32. The right target is at rows 26-30, cols 44-48. The barrier is at cols 33-38.\nWhat if the right frame needs to move UP first, then RIGHT, then DOWN to reach the target? But UP didn't work...\nActually, wait. Let me re-check. The UP action was executed, and the board changed (board_changed: true). But the frame position didn't change. What changed?\nLet me compare the before and after frames to see what actually changed.\nActually, I think I need to look at the transition. The UP action was executed, and the frame didn't move. But the board changed. What could have changed?\nOh wait, I just realized something. The UP action was executed AFTER the MOUSE action. The MOUSE action changed the center from charcoal to white. So the board_changed could be from the MOUSE action, not the UP action.\nBut the executed_actions shows both actions were executed. Let me check if the UP action actually moved the frame by looking at the transition.\nActually, I think the issue is that the frame is at the top of its movement range in the left panel. The left panel might only extend from rows 26-32, and the frame is at rows 30-32. Moving UP would put it at rows 27-29, but maybe the panel doesn't extend that far at cols 30-32.\nLooking at the ascii:\nRow 27: ggggggggppppppwwwwwcwwwcwwwwwg\nRow 28: ggggggggppppppwwwwwcwwwcwwwwwg\nRow 29: ggggggggppppppwwwwwcwwwcwwwwwg\nAt cols 30-32 in rows 27-29, it's gray (ggg). So the frame can't move UP because there's no white panel there.\nSo the right frame is stuck in the corridor at rows 30-32, cols 30-32. It can't move UP (gray area), can't move RIGHT (barrier), and can't move DOWN (probably gray area or panel edge).\nWait, but the frame was originally at rows 30-32, cols 30-32, and I moved it RIGHT multiple times to get here. So it could move RIGHT before. But now it can't move RIGHT because of the barrier.\nHmm, let me reconsider. Maybe the right frame is supposed to go to the LEFT target, not the right target? But the left target is already occupied by the left frame.\nOr maybe the right frame doesn't need to move at all, and the level is complete when both frames are in their correct positions? But the right frame is not in the right target.\nI'm stuck. Let me try a different approach. Let me check if the frame can move LEFT or DOWN.\nActually, wait. Let me re-examine the problem. The right frame is at rows 30-32, cols 30-32. The right target is at rows 26-30, cols 44-48. \nWhat if the right frame needs to go around the barrier? The barrier is at cols 33-38, rows 26-35 (approximately). If the frame could move DOWN past the barrier, then RIGHT, then UP, it could reach the right target.\nLet me try DOWN to see if the frame can move down.", "kind": "reasoning", "inContext": false}, {"label": "TOOL CALL: python", "content": "<tool_call>\n<function=python>\n<parameter=code>\n# Check what changed after UP+RIGHT\n# Frame still at rows 30-32, cols 30-32 - UP didn't move it, RIGHT didn't move it\n# Let me check if DOWN works\n\nseg = current_frame.segmentation\nnodes = seg['nodes']\nn_frames = [n for n in nodes if n['color'] == 'N']\nfor n in n_frames:\n    b = n['boundary']\n    print(f\"N frame: boundary={b}\")\n\n# Check ascii around frame\nascii = current_frame.ascii\nlines = ascii.split('\\n')\nprint(\"\\nRows 28-36, cols 25-40:\")\nfor r in range(28, 37):\n    print(f\"Row {r}: {lines[r][25:40]}\")\n\n# Try DOWN to see if frame can move down past barrier\naction(['DOWN'])\n</parameter>\n<parameter=world_model>\n{\"game_tier\": {\"action_semantics\": {\"RIGHT\": \"Moves active green frame right by 3 cols VERIFIED\", \"LEFT\": \"Moves active green frame left by 3 cols VERIFIED\", \"UP\": \"Moves active green frame up by 3 rows VERIFIED\", \"DOWN\": \"Moves active green frame down by 3 rows VERIFIED\", \"MOUSE\": \"Clicking on green frame selects it (gives white center) VERIFIED\"}, \"object_taxonomy\": {\"g\": \"gray background\", \"w\": \"white panels/squares\", \"p\": \"purple vertical bar\", \"N\": \"light green 3x3 frames (movable tokens)\", \"c\": \"charcoal 5x5 frames (targets)\", \"W\": \"white single pixel (selected token center)\", \"B\": \"black single pixel (unselected token center)\"}, \"hud_map\": {\"bottom_bar\": \"row 63, charcoal strip\"}, \"win_pattern\": {\"rule\": \"Move each green frame into a charcoal target frame\"}, \"level_log\": {}, \"cross_level_notes\": {}}, \"level_tier\": {\"world_model\": \"Left frame in left target. Right frame selected at rows 30-32, cols 30-32. UP and RIGHT both failed (blocked). Barrier at cols 33-38. Right target at rows 26-30, cols 44-48.\", \"goal_model\": \"Move right frame to right target, need to find path around barrier\", \"recent_findings\": [\"UP blocked for right frame (gray area above)\", \"RIGHT blocked (barrier)\"], \"open_questions\": [\"Can frame move DOWN past barrier?\", \"Is there a gap in the barrier?\"], \"current_plan\": \"Try DOWN to see if frame can move down\", \"strategy_log\": [], \"failed_probes\": [\"UP on right frame (blocked)\", \"RIGHT on right frame (barrier)\"]}}\n</parameter>\n</function>\n</tool_call>", "kind": "tool", "inContext": true}, {"label": "TOOL RESULT: python", "content": "N frame: boundary=[[30, 30], [30, 32], [32, 32], [32, 30]]\nN frame: boundary=[[33, 12], [33, 14], [35, 14], [35, 12]]\n\nRows 28-36, cols 25-40:\nRow 28: ggggggggppppppw\nRow 29: ggggggggppppppw\nRow 30: wwwwwNNNppppppw\nRow 31: wwwwwNWNppppppw\nRow 32: wwwwwNNNppppppw\nRow 33: ggggggggppppppw\nRow 34: ggggggggppppppw\nRow 35: ggggggggppppppw\nRow 36: ggggggggppppppw", "kind": "tool", "inContext": true}], "hasExactModelContext": false, "requestIndexWithinTurn": null, "messageCount": 0}}}